pypanrestv2/ApplicationHelper.py
pypanrestv2/Base.py
pypanrestv2/Device.py
pypanrestv2/Exceptions.py
pypanrestv2/Network.py
pypanrestv2/Objects.py
pypanrestv2/Panorama.py
pypanrestv2/Policies.py
pypanrestv2/XDR.py
pypanrestv2/__init__.py
pypanrestv2-2.1.2.dist-info/METADATA
pypanrestv2-2.1.2.dist-info/WHEEL
pypanrestv2-2.1.2.dist-info/RECORD
