Metadata-Version: 2.4
Name: PyPANRestV2
Version: 2.1.2
Summary: Python tools for interacting with Palo Alto Networks REST API.
License: MIT
Author: Mark Rzepa
Author-email: mark@rzepa.com
Requires-Python: >=3.11
Classifier: License :: OSI Approved :: MIT License
Classifier: Programming Language :: Python :: 3
Classifier: Programming Language :: Python :: 3.11
Classifier: Programming Language :: Python :: 3.12
Classifier: Programming Language :: Python :: 3.13
Classifier: Programming Language :: Python :: 3.14
Requires-Dist: dnspython (>=2.6.1)
Requires-Dist: icecream (>=2.1.3)
Requires-Dist: pycountry (>=23.12.11)
Requires-Dist: python-dotenv (>=1.0.1)
Requires-Dist: requests (>=2.31.0)
Requires-Dist: tqdm (>=4.66.2)
Requires-Dist: validators (>=0.22.0)
Requires-Dist: xmltodict (>=0.13.0)
